Metadata-Version: 1.1
Name: windchill
Version: 0.0.1
Summary: Useful methods for temp Sensors
Home-page: UNKNOWN
Author: Gary Ewing
Author-email: workburner4321@gmail.com
License: MIT
Keywords: temp Sensor Data
Platform: UNKNOWN
Classifier: Development Status :: 5 - Production/Stable
Classifier: Intended Audience :: Education
Classifier: Operating System :: Microsoft :: Windows :: Windows 10
Classifier: License :: OSI Approved :: MIT License
Classifier: Programming Language :: Python :: 3
